pypriority/__init__.py
pypriority-0.0.0rc0.dist-info/LICENSE
pypriority-0.0.0rc0.dist-info/METADATA
pypriority-0.0.0rc0.dist-info/WHEEL
pypriority-0.0.0rc0.dist-info/top_level.txt
pypriority-0.0.0rc0.dist-info/RECORD
